smarttasep/DQN.py
smarttasep/GridEnvironment.py
smarttasep/GridEnvironmentInterface.py
smarttasep/Hasel.py
smarttasep/Playground.py
smarttasep/Trainer.py
smarttasep/TrainerInterface.py
smarttasep/__init__.py
smarttasep-0.1.4.dist-info/licenses/LICENSE
smarttasep-0.1.4.dist-info/METADATA
smarttasep-0.1.4.dist-info/WHEEL
smarttasep-0.1.4.dist-info/top_level.txt
smarttasep-0.1.4.dist-info/RECORD
