Metadata-Version: 2.4
Name: smarttasep
Version: 0.1.4
Summary: A package implementing a Totally Asymmetric Simple Exclusion Process (TASEP) using reinforcement learning (RL) agents.
Author: Jonas Märtens
Project-URL: homepage, https://github.com/jonasmaertens/TASEP
Requires-Python: >=3.10
License-File: LICENSE
Requires-Dist: gymnasium
Requires-Dist: pygame
Requires-Dist: pyqt6
Requires-Dist: tabulate
Requires-Dist: torchrl
Requires-Dist: tqdm
Requires-Dist: matplotlib
Requires-Dist: numpy
Dynamic: license-file
